{
  "users": {
    "Leroy": {
      "password": "scrypt:32768:8:1$REPLACE_WITH_HASH_FOR_qwer1234",
      "clicks": 0
    },
    "QR-Code": {
      "password": "scrypt:32768:8:1$REPLACE_WITH_HASH_FOR_qwer1234",
      "clicks": 0
    },
    "Gast": {
      "password": "scrypt:32768:8:1$REPLACE_WITH_HASH_FOR_qwer1234",
      "clicks": 0
    }
  },
  "counters": {
    "Trockner": {
      "name": "Trockner",
      "color": "#db33bc",
      "weekly_count": 0,
      "total_count": 0,
      "weekly_clicks": [],
      "all_clicks": [],
      "reset_day": 6
    }
  }
}
